noob_gradio/__init__.py
noob_gradio/client.py
noob_gradio-1.2.0.dist-info/licenses/LICENSE
noob_gradio-1.2.0.dist-info/METADATA
noob_gradio-1.2.0.dist-info/WHEEL
noob_gradio-1.2.0.dist-info/top_level.txt
noob_gradio-1.2.0.dist-info/RECORD
