Metadata-Version: 2.4
Name: noob_gradio
Version: 1.2.0
Summary: A lightweight async alternative to gradio_client without heavy dependencies.
Author: Noob
License-Expression: MIT
Project-URL: Homepage, https://github.com/Noob-Lol/noob-gradio
Project-URL: Source, https://github.com/Noob-Lol/noob-gradio
Project-URL: Issues, https://github.com/Noob-Lol/noob-gradio/issues
Keywords: gradio,async,client,huggingface,api
Classifier: Programming Language :: Python :: 3
Classifier: Framework :: AsyncIO
Classifier: Topic :: Software Development :: Libraries :: Python Modules
Requires-Python: >=3.10
License-File: LICENSE
Requires-Dist: aiohttp>=3.9
Requires-Dist: anyio>=3.7
Dynamic: license-file
